moo/__init__.py
moo-0.5.5.dist-info/METADATA
moo-0.5.5.dist-info/WHEEL
moo-0.5.5.dist-info/entry_points.txt
moo-0.5.5.dist-info/top_level.txt
moo-0.5.5.dist-info/RECORD
